curvpy/__init__.py
curvpy/curvpy.py
CurvPy-3.0.2.dist-info/METADATA
CurvPy-3.0.2.dist-info/WHEEL
CurvPy-3.0.2.dist-info/top_level.txt
CurvPy-3.0.2.dist-info/RECORD
