Metadata-Version: 2.1
Name: CurvPy
Version: 3.0.2
Summary: A regression analysis library
Home-page: UNKNOWN
Author: sidharth
Author-email: sidharthss2690@gmail.com
License: UNKNOWN
Platform: UNKNOWN
Requires-Dist: matplotlib
Requires-Dist: numpy
Requires-Dist: pandas
Requires-Dist: scikit-learn
Requires-Dist: scipy
Requires-Dist: seaborn
